qloader/__init__.py
qloader/args.py
qloader/browserdriver.py
qloader/logger.py
qloader/query.py
qloader-8.4.5.dist-info/METADATA
qloader-8.4.5.dist-info/WHEEL
qloader-8.4.5.dist-info/RECORD
