Metadata-Version: 2.1
Name: qloader
Version: 8.4.5
Summary: Gather results from some search engine
Author: tasker
Author-email: tasker@ialcloud.xyz
Requires-Python: >=3.7,<4.0
Classifier: Programming Language :: Python :: 3
Classifier: Programming Language :: Python :: 3.7
Classifier: Programming Language :: Python :: 3.8
Classifier: Programming Language :: Python :: 3.9
Classifier: Programming Language :: Python :: 3.10
Classifier: Programming Language :: Python :: 3.11
Requires-Dist: imagehash
Requires-Dist: pillow
Requires-Dist: requests
Requires-Dist: selenium
